gfwlist2privoxy/__init__.py
gfwlist2privoxy/main.py
gfwlist2privoxy/resources/__init__.py
gfwlist2privoxy/resources/builtin.txt
gfwlist2privoxy/resources/gfwlist.action
gfwlist2privoxy/resources/tld.txt
gfwlist2privoxy/resources/white.action
gfwlist2privoxy-2.0.0.dist-info/LICENSE
gfwlist2privoxy-2.0.0.dist-info/METADATA
gfwlist2privoxy-2.0.0.dist-info/WHEEL
gfwlist2privoxy-2.0.0.dist-info/entry_points.txt
gfwlist2privoxy-2.0.0.dist-info/top_level.txt
gfwlist2privoxy-2.0.0.dist-info/RECORD
