Metadata-Version: 2.1
Name: gfwlist2privoxy
Version: 2.0.0
Summary: convert gfwlist to privoxy action file
Home-page: https://github.com/snachx/gfwlist2privoxy
Author: snachx
Author-email: snachx@gmail.com
License: MIT
Platform: UNKNOWN
Classifier: License :: OSI Approved :: MIT License
Classifier: Programming Language :: Python :: 3
Classifier: Programming Language :: Python :: 3.6
Classifier: Programming Language :: Python :: 3.7
Classifier: Programming Language :: Python :: 3.8
Classifier: Programming Language :: Python :: 3.9
Classifier: Programming Language :: Python :: 3.10
Requires-Python: >=3.6
License-File: LICENSE
